LICENSE
README.md
setup.cfg
setup.py
HeleketAPI/__init__.py
HeleketAPI/exceptions.py
HeleketAPI.egg-info/PKG-INFO
HeleketAPI.egg-info/SOURCES.txt
HeleketAPI.egg-info/dependency_links.txt
HeleketAPI.egg-info/top_level.txt
HeleketAPI/client/__init__.py
HeleketAPI/client/client.py
HeleketAPI/client/session/__init__.py
HeleketAPI/client/session/_aiohttp.py
HeleketAPI/client/session/base.py
HeleketAPI/enums/__init__.py
HeleketAPI/enums/base_enum.py
HeleketAPI/enums/blockchain.py
HeleketAPI/enums/crypto_currency.py
HeleketAPI/enums/fiat_currency.py
HeleketAPI/enums/payment_status.py
HeleketAPI/methods/__init__.py
HeleketAPI/methods/base.py
HeleketAPI/methods/create_invoice.py
HeleketAPI/methods/create_wallet.py
HeleketAPI/methods/generate_qr.py
HeleketAPI/methods/get_payment_info.py
HeleketAPI/methods/refund.py
HeleketAPI/methods/test_webhook.py
HeleketAPI/types/__init__.py
HeleketAPI/types/base.py
HeleketAPI/types/money_amount.py
HeleketAPI/types/payment_info_response.py
HeleketAPI/types/qr_response.py
HeleketAPI/types/refund_response.py
HeleketAPI/types/test_webhook.py
HeleketAPI/types/wallet_response.py