Metadata-Version: 2.4
Name: HeleketAPI
Version: 0.0.5.dev0
Summary: Easy interaction with Heleket API, support for asynchronous approaches
Author: Fsoky
Author-email: cyberuest0x12@gmail.com
License: MIT
Keywords: api heleket asyncio crypto heleketapi
License-File: LICENSE
Dynamic: author
Dynamic: author-email
Dynamic: description
Dynamic: description-content-type
Dynamic: keywords
Dynamic: license
Dynamic: license-file
Dynamic: summary
